{
  "id": "root",
  "commands": [
    {
      "id": "get_order_state",
      "button_text": "Узнать состояние заказа",
      "text": "Введите номер заказа",
      "wait_input": true,
      "handler": "get_order_state"
    },
    {
      "id": "learning",
      "button_text": "Узнать телефон магазина",
      "text": "Магазины какого города вас интересуют?",
      "commands": [
        {
          "id": "msk",
          "button_text": "Москва",
          "handler": "get_shop_phones"
        },
        {
          "id": "spb",
          "button_text": "Санкт-Петербург",
          "handler": "get_shop_phones"
        },
        {
          "id": "vld",
          "button_text": "Владивосток",
          "handler": "get_shop_phones"
        }
      ]
    },
    {
      "id": "qa",
      "button_text": "Узнать телефон сервиса",
      "text": "Задайте вопрос в произвольной форме",
      "wait_input": true,
      "handler" : "handle_get_answers"
    }
  ]
}